as_models/__init__.py
as_models/api_user.py
as_models/app_configuration.py
as_models/client_utils.py
as_models/data_number.py
as_models/data_storage_type.py
as_models/email_notifications.py
as_models/grow_month.py
as_models/grow_week.py
as_models/image.py
as_models/inventory_active_items.py
as_models/item_month.py
as_models/item_month_notes.py
as_models/item_month_supply.py
as_models/item_reserve.py
as_models/item_week.py
as_models/item_week_notes.py
as_models/item_week_supply.py
as_models/logging_message.py
as_models/quick_storage.py
as_models/reporting_config.py
as_models/reserve_summary.py
as_models/sales_inv_utils.py
as_models/storage_blob.py
as_models/supplier.py
as_models/utils.py
as_models/analytics/__init__.py
as_models/analytics/big_query_staging.py
as_models/analytics/firestore_trigger.py
as_models/pub_sub/__init__.py
as_models/quickbooks/__init__.py
as_models/rest/__init__.py
as_models/rest/sales_inv.py
as_models/spreadsheets/__init__.py
as_models/spreadsheets/utils.py
as_models/tasks/__init__.py
AS_Object_models-2.3.9.dist-info/METADATA
AS_Object_models-2.3.9.dist-info/WHEEL
AS_Object_models-2.3.9.dist-info/top_level.txt
AS_Object_models-2.3.9.dist-info/RECORD
