Metadata-Version: 2.1
Name: AS-Object-models
Version: 2.3.9
Summary: A Project that captures all of the data manipulation used in apps developed by Analytics Supply LLC.
Home-page: https://gitlab.com/AnalyticsSupply/as-object-models
Author: Jason Bowles
Author-email: jasonbowles@analyticssupply.com
License: MIT
Platform: UNKNOWN
Classifier: License :: OSI Approved :: MIT License
Classifier: Programming Language :: Python
Requires-Python: >=3.6
Requires-Dist: docutils (>=0.3)
Requires-Dist: pandas (>=1.0.3)
Requires-Dist: jmespath (>=0.9.3)
Requires-Dist: python-dateutil (>=2.8.1)
Requires-Dist: mailjet-rest (>=1.3.3)
